dfndfl-1.1.1.dist-info/METADATA
dfndfl-1.1.1.dist-info/WHEEL
dfndfl-1.1.1.dist-info/entry_points.txt
dfndfl-1.1.1.dist-info/licenses/LICENSE
dfndfl/__init__.py
dfndfl/cs_dfn.py
dfndfl/mixed_DFN_DFLINT.py
dfndfl/problem_runner.py
dfndfl/run.py
dfndfl-1.1.1.dist-info/RECORD
