Metadata-Version: 2.1
Name: dfndfl
Version: 1.1.1
Summary: A package implementing DFNDFL, an algorithm that solves mixed-integer nonsmooth constrained optimization problems whose constraint functions are avaliable only as the oytput of a black-box zeroth-order oracle.
Author-Email: Andrea Petruzzi <petruzzi.1982874@studenti.uniroma1.it>, Tommaso Giovannelli <giovanto@ucmail.uc.edu>, Giampaolo Liuzzi <liuzzi@diag.uniroma1.it>, Stefano Lucidi <lucidi@diag.uniroma1.it>, Francesco Rinaldi <rinaldi@math.unipd.it>
License: GNU GENERAL PUBLIC LICENSE
Classifier: Programming Language :: Python :: 3
Classifier: License :: OSI Approved :: GNU General Public License (GPL)
Classifier: Operating System :: OS Independent
Project-URL: Homepage, https://github.com/GreyJolly/DFNDFL-Package/
Requires-Python: >=3.9
Requires-Dist: ghalton
Requires-Dist: numpy
Requires-Dist: sobol_seq
